[
    { "itemName": "pendant",

      "passiveStats": "",
      "itemSlot": "",
      "tags": "",
      "desc": "A set of small steel trinkets on a thin rope.",
      "itemRarity": "",

      "actions":{
        "actionName": "transfer",
        "tags": "utility",
        "desc": "swap your power with enemy",
        "passiveStats": "",
        "actionMod": "",
        "actionCharge": 12,
        "cooldown": "",
        "keyId": 70,
        "actionType": ""
      }
    },
    { "itemName": "wizards hand",    
      "actions": {
        "actionName": "stress",
        "tags": "utility",
        "desc": "enemy won't repeat this turns action while this is on cooldown (3-6 turns)",
        "passiveStats": "",
        "actionMod": 6,
        "actionCharge": 12,
        "cooldown": 6,
        "keyId": 68,
        "actionType": "variable cooldown"
      },
      "passiveStats": "",
      "itemSlot": "",
      "tags": "",
      "desc": "",
      "itemRarity": ""
    },
    { "itemName": "carabiner",
      "actions": {
        "actionName": "pull",
        "tags": "utility",
        "desc": "unequip this to equip an item from the inventory (instant)",
        "passiveStats": "",
        "actionMod": "",
        "actionCharge": 20,
        "cooldown": "",
        "keyId": 67,
        "actionType": "extra-action"
      },
      "passiveStats": "",
      "itemSlot": "",
      "tags": "",
      "desc": "",
      "itemRarity": ""
    },
    { "itemName": "red cross kit",
      "actions": {
        "actionName": "first aid",
        "tags": "passive",
        "desc": "restore 3 life at the end of the fight",
        "passiveStats": "",
        "actionMod": 3,
        "actionCharge": 1,
        "cooldown": "",
        "keyId": 66,
        "actionType": "passive"
      },
      "passiveStats": "",
      "itemSlot": "",
      "tags": "",
      "desc": "bag filled with drugs and first aid items. On the inside you can see a distorted print 'Volunteer for victory 1 5 ed Cro'",
      "itemRarity": ""
    },
    { "itemName": "axe",
      "actions": {
        "actionName": "axe attack",
        "tags": "attack",
        "desc": "pay 4 (+power) life, deal 1 dmg per 2 missing life",
        "passiveStats": "",
        "actionMod": 4,
        "actionCharge": 60,
        "cooldown": "",
        "keyId": 8,
        "actionType": ""
      },
      "passiveStats": "",
      "itemSlot": "",
      "tags": "weapon",
      "desc": "",
      "itemRarity": ""
    },
    { "itemName": "great axe",
      "actions": {
        "actionName": "great axe attack",
        "tags": "attack",
        "desc": "attack for 25% of enemy life (+5% per power)",
        "passiveStats": "",
        "actionMod": 25,
        "actionCharge": 60,
        "cooldown": "",
        "keyId": 65,
        "actionType": ""
      },
      "passiveStats": "",
      "itemSlot": "",
      "tags": "weapon",
      "desc": "",
      "itemRarity": ""
    },
    { "itemName": "sickle",
      "actions": {
        "actionName": "sickle attack",
        "tags": "attack, poison",
        "desc": "deal 2 dmg. Poisons on hit",
        "passiveStats": "",
        "actionMod": 1,
        "actionCharge": 60,
        "cooldown": "",
        "keyId": 64,
        "actionType": ""
      },
      "passiveStats": "",
      "itemSlot": "",
      "tags": "weapon",
      "desc": "",
      "itemRarity": ""
    },
    { "itemName": "spear",
      "actions": {
        "actionName": "spear attack",
        "tags": "attack, breaks def",
        "desc": "deal dmg equal to dice roll no more than 4. Breaks def",
        "passiveStats": "",
        "actionMod": 4,
        "actionCharge": 60,
        "cooldown": "",
        "keyId": 63,
        "actionType": ""
      },
      "passiveStats": "",
      "itemSlot": "",
      "tags": "weapon",
      "desc": "modeled after ancient hunting tools, this spear boasts a straight hardwood shaft topped with a tempered iron head. Practical and utilitarian",
      "itemRarity": ""
    },
    { "itemName": "wooden staff",
      "actions": {
        "actionName": "focus",
        "tags": "",
        "desc": "gain 1 power per 4 dice roll",
        "passiveStats": "",
        "actionMod": 1,
        "actionCharge": 60,
        "cooldown": 2,
        "keyId": 48,
        "actionType": ""
      },
      "passiveStats": "",
      "itemSlot": "",
      "tags": "weapon",
      "desc": "",
      "itemRarity": ""
    },
    { "itemName": "club",
      "actions": {
        "actionName": "club attack",
        "tags": "attack",
        "desc": "deal 3 dmg",
        "passiveStats": "",
        "actionMod": 3,
        "actionCharge": 300,
        "cooldown": "",
        "keyId": 45,
        "actionType": ""
      },
      "passiveStats": "",
      "itemSlot": "",
      "tags": "weapon",
      "desc": "",
      "itemRarity": ""
    },
    { "itemName": "hammer",
        "actions": {
            "actionName": "armor breaker",
            "tags": "attack",
            "desc": "deal 4 dmg, this attack breaks defence",
            "passiveStats": "",
            "actionMod": "",
            "actionCharge": "",
            "cooldown": "",
            "keyId": "",
            "actionType": ""
        },
        "tags": "curse",
        "desc": "reduce enemy def by your def value, loose 1 def",
        "passiveStats": "",
        "actionMod": "",
        "actionCharge": 16,
        "cooldown": "",
        "keyId": 2,
        "actionType": ""
    },
    { "itemName": "mace",
      "actions": {
        "actionName": "mace attack",
        "tags": "attack",
        "desc": "deal 3 dmg. Gain 1 def if your dice roll is 4",
        "passiveStats": "",
        "actionMod": 3,
        "actionCharge": 60,
        "cooldown": "",
        "keyId": 1,
        "actionType": ""
      },
      "passiveStats": "",
      "itemSlot": "",
      "tags": "weapon",
      "desc": "",
      "itemRarity": ""
    },
    { "itemName": "dagger",
      "actions": {
        "actionName": "cut",
        "tags": "",
        "desc": "deal 1 dmg (cost 3 dice roll, instant)",
        "passiveStats": "",
        "actionMod": 1,
        "actionCharge": 24,
        "cooldown": "",
        "keyId": 6,
        "actionType": "extra-action"
      },
      "passiveStats": "",
      "itemSlot": "",
      "tags": "weapon",
      "desc": "",
      "itemRarity": ""
    },
    { "itemName": "dagger pair",
      "actions": {
        "actionName": "dagger attack",
        "tags": "attack, multistrike",
        "desc": "deal 1 dmg twice",
        "passiveStats": "",
        "actionMod": 1,
        "actionCharge": 60,
        "cooldown": "",
        "keyId": 4,
        "actionType": ""
      },
      "passiveStats": "",
      "itemSlot": "",
      "tags": "weapon",
      "desc": "",
      "itemRarity": ""
    },
    { "itemName": "sword",
      "actions": {
        "actionName": "sword attack",
        "tags": "attack",
        "desc": "deal 3 dmg. Temporary +1 dmg if dice roll is 5 or 6",
        "passiveStats": "",
        "actionMod": 3,
        "actionCharge": 300,
        "cooldown": "",
        "keyId": 7,
        "actionType": ""
      },
      "passiveStats": "",
      "itemSlot": "",
      "tags": "weapon",
      "desc": "a weapon shaped by the forgotten age. Wield it as a silent hymn to the lost glories of previous owners, its edge is a faithful companion in a world longing for heroes",
      "itemRarity": ""
    },
    { "itemName": "bow",
      "actions": {
        "actionName": "bow attack",
        "tags": "attack",
        "desc": "deal dmg equal to your dice roll value",
        "passiveStats": "",
        "actionMod": "",
        "actionCharge": 50,
        "cooldown": "",
        "keyId": 5,
        "actionType": ""
      },
      "passiveStats": "",
      "itemSlot": "",
      "tags": "weapon",
      "desc": "this longbow embodies the craftsmanship of a bygone era. Hemp strings ensure a powerful draw, while simplicity in design reflects the practicality valued in these turbulent times",
      "itemRarity": ""
    },
    { "itemName": "hook",
      "actions": {
        "actionName": "swap",
        "tags": "utility",
        "desc": "swap dice rolls (instant)",
        "passiveStats": "",
        "actionMod": "",
        "actionCharge": 12,
        "cooldown": "",
        "keyId": 52,
        "actionType": "extra-action"
      },
      "passiveStats": "",
      "itemSlot": "",
      "tags": "equipment",
      "desc": "",
      "itemRarity": ""
    },
    { "itemName": "wizards head",
      "actions": {
        "actionName": "fear",
        "tags": "utility",
        "desc": "force enemy to block while this is on cooldown (cooldown 2-4 turns)",
        "passiveStats": "",
        "actionMod": "",
        "actionCharge": 12,
        "cooldown": 4,
        "keyId": 55,
        "actionType": "variable cooldown"
      },
      "passiveStats": "",
      "itemSlot": "",
      "tags": "off-hand",
      "desc": "",
      "itemRarity": ""
    },
    { "itemName": "gonfalon",
      "actions": {
        "actionName": "defensive stance",
        "tags": "utility",
        "desc": "once per turn, reduce dice roll by 1 (instant)",
        "passiveStats": "",
        "actionMod": 1,
        "actionCharge": 40,
        "cooldown": "",
        "keyId": 50,
        "actionType": "extra-action"
      },
      "passiveStats": "",
      "itemSlot": "",
      "tags": "off-hand",
      "desc": "",
      "itemRarity": ""
    },
    { "itemName": "iron cross",
      "actions": {
        "actionName": "zealotry",
        "tags": "buff",
        "desc": "reduce def by dice roll to gain that much power",
        "passiveStats": "",
        "actionMod": "",
        "actionCharge": 12,
        "cooldown": 2,
        "keyId": 49,
        "actionType": ""
      },
      "passiveStats": "",
      "itemSlot": "",
      "tags": "off-hand",
      "desc": "",
      "itemRarity": ""
    },
    { "itemName": "spiked shield",
      "actions": {
        "actionName": "bash",
        "tags": "",
        "desc": "gain 1 def. On die roll of 1 stun the enemy",
        "passiveStats": "def:1",
        "actionMod": "",
        "actionCharge": 40,
        "cooldown": "",
        "keyId": 12,
        "actionType": ""
      },
      "passiveStats": "",
      "itemSlot": "",
      "tags": "off-hand",
      "desc": "",
      "itemRarity": ""
    },
    {"itemName": "wooden shield",
      "actions": {
        "actionName": "defend",
        "tags": "block, defensive",
        "desc": "reduce incoming dmg by 3",
        "passiveStats": "",
        "actionMod": 3,
        "actionCharge": 30,
        "cooldown": "",
        "keyId": 69,
        "actionType": ""
      },
      "passiveStats": "",
      "itemSlot": "",
      "tags": "off-hand",
      "desc": "",
      "itemRarity": ""
    },
    { "itemName": "shield",
      "actions": {
        "actionName": "block",
        "tags": "block, defensive",
        "desc": "reduce incoming dmg by dice roll value",
        "passiveStats": "",
        "actionMod": "",
        "actionCharge": 60,
        "cooldown": "",
        "keyId": 42,
        "actionType": ""
      },
      "passiveStats": "",
      "itemSlot": "",
      "tags": "off-hand",
      "desc": "common in the early Middle Ages, round shields featured resilient wood. Enhanced with metal, the shield's design, allows to deflect incoming blows",
      "itemRarity": ""
    },
    { "itemName": "tower shield",
      "actions": {
        "actionName": "heavy block",
        "tags": "block, defensive",
        "desc": "reduce incoming damage by 200% of your def",
        "passiveStats": "",
        "actionMod": 200,
        "actionCharge": 30,
        "cooldown": "",
        "keyId": 60,
        "actionType": ""
      },
      "passiveStats": "",
      "itemSlot": "",
      "tags": "off-hand",
      "desc": "",
      "itemRarity": ""
    },
    { "itemName": "kite shield",
      "actions": {
        "actionName": "side block",
        "tags": "block, defensive",
        "desc": "reduce incoming dmg by this actions charge value",
        "passiveStats": "",
        "actionMod": "",
        "actionCharge": 10,
        "cooldown": "",
        "keyId": 71,
        "actionType": ""
      },
      "passiveStats": "",
      "itemSlot": "",
      "tags": "off-hand",
      "desc": "",
      "itemRarity": ""
    },
    { "itemName": "bomb assembly kit",
      "actions": {
        "actionName": "inferno",
        "tags": "spell",
        "desc": "deal dmg equal to your power per every coin. Loose all coins",
        "passiveStats": "",
        "actionMod": "",
        "actionCharge": 30,
        "cooldown": "",
        "keyId": 54,
        "actionType": ""
      },
      "passiveStats": "",
      "itemSlot": "",
      "tags": "scroll",
      "desc": "",
      "itemRarity": ""
    },
    { "itemName": "acid vial",
      "actions": {
        "actionName": "wound",
        "tags": "curse",
        "desc": "reduce targets def by 4",
        "passiveStats": "",
        "actionMod": 4,
        "actionCharge": 3,
        "cooldown": "",
        "keyId": 22,
        "actionType": ""
      },
      "passiveStats": "",
      "itemSlot": "",
      "tags": "scroll",
      "desc": "",
      "itemRarity": ""
    },
    { "itemName": "thorns crown",
      "actions": {
        "actionName": "rage",
        "tags": "passive",
        "desc": "you do and take 200% dmg",
        "passiveStats": "",
        "actionMod": 200,
        "actionCharge": "",
        "cooldown": "",
        "keyId": 43,
        "actionType": "passive"
      },
      "passiveStats": "",
      "itemSlot": "",
      "tags": "helmet",
      "desc": "",
      "itemRarity": "unique"
    },
    { "itemName": "ring of endurance",
      "actions": {
        "actionName": "endurance charge",
        "tags": "passive",
        "desc": "adds 25% life while in action bar",
        "passiveStats": "life%:25",
        "actionMod": 25,
        "actionCharge": 1,
        "cooldown": "",
        "keyId": 28,
        "actionType": ""
      },
      "passiveStats": "",
      "itemSlot": "",
      "tags": "ring",
      "desc": "",
      "itemRarity": ""
    },
    { "itemName": "ring of twilight",
      "actions": [{
        "actionName": "order charge",
        "tags": "passive",
        "desc": "reduces dice by 2 while in action bar",
        "passiveStats": "dice-mod:-2",
        "actionMod": 2,
        "actionCharge": 1,
        "cooldown": "",
        "keyId": 29,
        "actionType": ""
      },
      {
        "actionName": "chaos charge",
        "tags": "passive",
        "desc": "adds 2 dice while in action bar",
        "passiveStats": "dice-mod:2",
        "actionMod": 2,
        "actionCharge": 1,
        "cooldown": "",
        "keyId": 30,
        "actionType": ""
      }],
      "passiveStats": "",
      "itemSlot": "",
      "tags": "ring",
      "desc": "",
      "itemRarity": "unique"
    },
    { "itemName": "ring of power",
      "actions": {
        "actionName": "power charge",
        "tags": "passive",
        "desc": "adds 1 power while in action bar",
        "passiveStats": "power:1",
        "actionMod": 1,
        "actionCharge": 1,
        "cooldown": "",
        "keyId": 32,
        "actionType": ""
      },
      "passiveStats": "",
      "itemSlot": "",
      "tags": "ring",
      "desc": "",
      "itemRarity": "unique"
    },
    { "itemName": "decacore",
      "actions": "",
      "passiveStats": "dice:10, life:-6",
      "itemSlot": "dice",
      "tags": "dice",
      "desc": "",
      "itemRarity": "rare"
    },
    { "itemName": "tetracore",
      "actions": "",
      "passiveStats": "dice:4, def:2",
      "itemSlot": "dice",
      "tags": "dice",
      "desc": "",
      "itemRarity": "unique"
    },
    { "itemName": "dodecacore",
      "actions": "",
      "passiveStats": "dice:12, def:-1, power:-1",
      "itemSlot": "dice",
      "tags": "dice",
      "desc": "a deceptively small jewel possessing an insidious charm. Unstable cores tend to influence the minds of those who posses them, compelling them towards acts of greed, and recklessness",
      "itemRarity": "unique"
    },
    { "itemName": "octocore",
      "actions": "",
      "passiveStats": "dice:8, def:-1",
      "itemSlot": "dice",
      "tags": "dice",
      "desc": "",
      "itemRarity": "rare"
    },
    { "itemName": "plate armor",
      "actions": "",
      "passiveStats": "def:2",
      "itemSlot": "body",
      "tags": "body armor",
      "desc": "",
      "itemRarity": ""
    },
    { "itemName": "robe",
      "actions": {
        "actionName": "power surge",
        "tags": "passive",
        "desc": "gain 1 power on a die roll greater than 7",
        "passiveStats": "",
        "actionMod": 1,
        "actionCharge": "",
        "cooldown": "",
        "keyId": 58,
        "actionType": "passive"
      },
      "passiveStats": "",
      "itemSlot": "body",
      "tags": "body armor",
      "desc": "full body garment with long sleeves. The sleeves have few belts that can be tied to the back of the jacket to restrict motion",
      "itemRarity": ""
    },
    { "itemName": "gambison",
      "actions": "",
      "passiveStats": "life:12",
      "itemSlot": "body",
      "tags": "body armor",
      "desc": "",
      "itemRarity": ""
    },
    { "itemName": "chainmail",
      "actions": "",
      "passiveStats": "life:6, def:1",
      "itemSlot": "body",
      "tags": "body armor",
      "desc": "",
      "itemRarity": ""
    },
    { "itemName": "woolen bag",
      "actions": "",
      "passiveStats": "slots:5, def:-1, life:-6",
      "itemSlot": "bag",
      "tags": "bag",
      "desc": "",
      "itemRarity": "unique"
    },
    { "itemName": "leather bag",
      "actions": "",
      "passiveStats": "slots:4, def:-1",
      "itemSlot": "bag",
      "tags": "bag",
      "desc": "",
      "itemRarity": "rare"
    },
    { "itemName": "bag",
      "actions": "",
      "passiveStats": "slots:3",
      "itemSlot": "bag",
      "tags": "bag",
      "desc": "",
      "itemRarity": ""
    },
    { "itemName": "adrenaline pen",
      "actions": {
        "actionName": "adrenaline shot",
        "tags": "buff",
        "desc": "increase dice roll by 4 (instant)",
        "passiveStats": "",
        "actionMod": 4,
        "actionCharge": 6,
        "cooldown": "",
        "keyId": 39,
        "actionType": "extra-action"
      },
      "passiveStats": "",
      "itemSlot": "",
      "tags": "",
      "desc": "",
      "itemRarity": ""
    },
    { "itemName": "leather boots",
      "actions": {
        "actionName": "roll",
        "tags": "utility",
        "desc": "reroll your dice (instant)",
        "passiveStats": "",
        "actionMod": "",
        "actionCharge": 6,
        "cooldown": "",
        "keyId": 19,
        "actionType": "extra-action"
      },
      "passiveStats": "",
      "itemSlot": "",
      "tags": "boots",
      "desc": "",
      "itemRarity": ""
    },
    { "itemName": "boots",
      "actions": {
        "actionName": "preparation",
        "tags": "utility",
        "desc": "keep half of your dice roll for the next turn",
        "passiveStats": "",
        "actionMod": "",
        "actionCharge": 16,
        "cooldown": "",
        "keyId": 18,
        "actionType": ""
      },
      "passiveStats": "",
      "itemSlot": "",
      "tags": "boots",
      "desc": "",
      "itemRarity": ""
    },
    { "itemName": "cape",
      "actions": {
        "actionName": "dodge",
        "tags": "buff, defensive",
        "desc": "gain 35% chance to dodge next attack (+10% per dice roll point)",
        "passiveStats": "",
        "actionMod": 10,
        "actionCharge": 30,
        "cooldown": "",
        "keyId": 35,
        "actionType": ""
      },
      "passiveStats": "",
      "itemSlot": "",
      "tags": "cape",
      "desc": "a piece of tent fabric in the shape of a raincoat. This makes the owner a difficult target from a distance. You can see a small label that says 'Berghaus'.",
      "itemRarity": ""
    },
    { "itemName": "helmet",
      "actions": {
        "actionName": "tank",
        "tags": "defensive",
        "desc": "dmg taken can't exceed your die roll while this is on cooldown (cd 2-4 turns)",
        "passiveStats": "",
        "actionMod": "",
        "actionCharge": 12,
        "cooldown": 4,
        "keyId": 38,
        "actionType": "variable cooldown"
      },
      "passiveStats": "",
      "itemSlot": "",
      "tags": "",
      "desc": "",
      "itemRarity": ""
    },
    { "itemName": "bandages",
      "actions": {
        "actionName": "bandage wounds",
        "tags": "healing",
        "desc": "restore 4 life",
        "passiveStats": "",
        "actionMod": 4,
        "actionCharge": 12,
        "cooldown": "",
        "keyId": 61,
        "actionType": ""
      },
      "passiveStats": "",
      "itemSlot": "",
      "tags": "consumable",
      "desc": "",
      "itemRarity": ""
    },
    { "itemName": "smoke bomb",
      "actions": {
        "actionName": "smoke bomb",
        "tags": "croud control",
        "desc": "stuns the enemy",
        "passiveStats": "",
        "actionMod": "",
        "actionCharge": 12,
        "cooldown": "",
        "keyId": 47,
        "actionType": ""
      },
      "passiveStats": "",
      "itemSlot": "",
      "tags": "consumable",
      "desc": "",
      "itemRarity": ""
    },
    { "itemName": "sal ammoniac",
      "actions": {
        "actionName": "restoration",
        "tags": "utility",
        "desc": "reset dice, power and def. Heal 1 life per restored point",
        "passiveStats": "",
        "actionMod": 0,
        "actionCharge": 12,
        "cooldown": "",
        "keyId": 44,
        "actionType": ""
      },
      "passiveStats": "",
      "itemSlot": "",
      "tags": "consumable",
      "desc": "smelling salts have been used on people feeling faint, or who have fainted. They are usually administered by others but may be self-administered",
      "itemRarity": ""
    },
    { "itemName": "water potion",
      "actions": {
        "actionName": "water potion",
        "tags": "buff",
        "desc": "gain 3 power until the end of encounter",
        "passiveStats": "",
        "actionMod": 3,
        "actionCharge": 3,
        "cooldown": "",
        "keyId": 40,
        "actionType": ""
      },
      "passiveStats": "",
      "itemSlot": "",
      "tags": "consumable, potion",
      "desc": "",
      "itemRarity": ""
    },
    { "itemName": "poison potion",
      "actions": {
        "actionName": "weapon poison",
        "tags": "enchantment",
        "desc": "next time you attack, all hits during that turn will poison (instant)",
        "passiveStats": "",
        "actionMod": "",
        "actionCharge": 24,
        "cooldown": "",
        "keyId": 41,
        "actionType": "extra-action"
      },
      "passiveStats": "",
      "itemSlot": "",
      "tags": "consumable, potion",
      "desc": "",
      "itemRarity": ""
    },
    { "itemName": "caltrops",
      "actions": {
        "actionName": "slow",
        "tags": "curse",
        "desc": "reduce targets dice roll by 4 (instant)",
        "passiveStats": "",
        "actionMod": 4,
        "actionCharge": 12,
        "cooldown": "",
        "keyId": 24,
        "actionType": "extra-action"
      },
      "passiveStats": "",
      "itemSlot": "",
      "tags": "consumable",
      "desc": "",
      "itemRarity": ""
    },
    { "itemName": "beladonna darts",
      "actions": {
        "actionName": "weaken",
        "tags": "curse",
        "desc": "reduce targets power by 2",
        "passiveStats": "",
        "actionMod": 2,
        "actionCharge": 3,
        "cooldown": "",
        "keyId": 21,
        "actionType": ""
      },
      "passiveStats": "",
      "itemSlot": "",
      "tags": "consumable, scroll",
      "desc": "",
      "itemRarity": ""
    },
    { "itemName": "healing potion",
      "actions": {
        "actionName": "healing potion",
        "tags": "buff, defensive",
        "desc": "restore half of the missing life",
        "passiveStats": "",
        "actionMod": 50,
        "actionCharge": 3,
        "cooldown": "",
        "keyId": 33,
        "actionType": ""
      },
      "passiveStats": "",
      "itemSlot": "",
      "tags": "consumable, potion",
      "desc": "",
      "itemRarity": ""
    },
    { "itemName": "papaver somniferum",
      "actions": {
        "actionName": "fortify",
        "tags": "buff, defensive",
        "desc": "gain 4 def until the end of encounter",
        "passiveStats": "",
        "actionMod": 4,
        "actionCharge": 3,
        "cooldown": "",
        "keyId": 34,
        "actionType": ""
      },
      "passiveStats": "",
      "itemSlot": "",
      "tags": "consumable",
      "desc": "",
      "itemRarity": ""
    },
    { "itemName": "sigil of light",
      "actions": {
        "actionName": "faith",
        "tags": "passive",
        "desc": "gain 2 max life every time your healing exceeds max life",
        "passiveStats": "",
        "actionMod": 2,
        "actionCharge": "",
        "cooldown": "",
        "keyId": 56,
        "actionType": "passive"
      },
      "passiveStats": "",
      "itemSlot": "",
      "tags": "jewelry",
      "desc": "",
      "itemRarity": ""
    },
    { "itemName": "alchemists key",
      "actions": {
        "actionName": "transmute",
        "tags": "utility",
        "desc": "gain 1 coin per dice roll. Requires dice roll 1 or 2",
        "passiveStats": "",
        "actionMod": "",
        "actionCharge": 40,
        "cooldown": "",
        "keyId": 53,
        "actionType": ""
      },
      "passiveStats": "",
      "itemSlot": "",
      "tags": "jewelry",
      "desc": "",
      "itemRarity": ""
    },
    { "itemName": "pauldron",
      "actions": {
        "actionName": "armor up",
        "tags": "passive",
        "desc": "gain 1 def on a die roll of 4",
        "passiveStats": "",
        "actionMod": 1,
        "actionCharge": "",
        "cooldown": "",
        "keyId": 59,
        "actionType": "passive"
      },
      "passiveStats": "",
      "itemSlot": "",
      "tags": "shoulder",
      "desc": "",
      "itemRarity": ""
    }
  ]